affirm.py
setup.py
affirm.egg-info/PKG-INFO
affirm.egg-info/SOURCES.txt
affirm.egg-info/dependency_links.txt
affirm.egg-info/top_level.txt