Metadata-Version: 1.0
Name: affirm
Version: 0.9.2
Summary: Improved error messages for Python assert statements
Home-page: https://github.com/gooli/affirm
Author: Eli Finer
Author-email: eli.finer@gmail.com
License: UNKNOWN
Platform: UNKNOWN
